quantize_fasttext/__init__.py
quantize_fasttext/main.py
quantize_fasttext-0.1.3.dist-info/METADATA
quantize_fasttext-0.1.3.dist-info/WHEEL
quantize_fasttext-0.1.3.dist-info/entry_points.txt
quantize_fasttext-0.1.3.dist-info/RECORD
