Metadata-Version: 2.1
Name: quantize-fasttext
Version: 0.1.3
Summary: 量化fasttext并测试其性能
Author: wangmengdi
Author-email: wangmengdi@pachiratech.com
Requires-Python: >=3.7
Classifier: Programming Language :: Python :: 3
Classifier: Programming Language :: Python :: 3.7
Classifier: Programming Language :: Python :: 3.8
Classifier: Programming Language :: Python :: 3.9
Classifier: Programming Language :: Python :: 3.10
Classifier: Programming Language :: Python :: 3.11
Requires-Dist: fasttext (>=0.9.2)
Requires-Dist: jsonargparse[signatures] (>=4.26.0)
Requires-Dist: wasabi (>=1.1.2)
